pxm_tools/Proxmox.py
pxm_tools/__init__.py
pxm_tools/py.typed
pxm_tools/cli/create.py
pxm_tools/cli/edit.py
pxm_tools/cli/help.py
pxm_tools/cli/remove.py
pxm_tools/cli/start.py
pxm_tools/cli/stop.py
pxm_tools-0.1.5.dist-info/METADATA
pxm_tools-0.1.5.dist-info/WHEEL
pxm_tools-0.1.5.dist-info/entry_points.txt
pxm_tools-0.1.5.dist-info/licenses/LICENSE
pxm_tools-0.1.5.dist-info/RECORD
