Metadata-Version: 2.4
Name: pxm-tools
Version: 0.1.5
Summary: A collection of tools to interact with Proxmox API.
Author-email: Leonardo Almeida <leonardoalmeida7777@gmail.com>
License-File: LICENSE
Requires-Python: >=3.12
Requires-Dist: python-dotenv>=1.1.0
Requires-Dist: requests>=2.32.3
Requires-Dist: rich>=14.0.0
